{
  "fondo_id": "progresion deuda lp",
  "nombre": "Progresion Deuda Lp",
  "nombre_cmf": "PROGRESION DEUDA LP",
  "tipo_fondo": "Mixto",
  "perfil_riesgo": "Medio",
  "descripcion_amigable": "El fondo Progresion Deuda Lp es una opción de inversión mixta que combina activos de renta fija y variable buscando un equilibrio entre rendimiento y seguridad. Esta estrategia tiene como objetivo principal generar ganancias a largo plazo, manteniendo un nivel de riesgo moderado. Aunque la composición exacta del fondo no está disponible públicamente, generalmente los fondos mixtos suelen diversificar su cartera en bonos, acciones y otros instrumentos financieros.\n\nEste tipo de fondo es adecuado para inversores con un perfil de riesgo medio, es decir, aquellos que buscan un equilibrio entre la seguridad de su capital y la posibilidad de obtener rendimientos superiores a los ofrecidos por instrumentos de renta fija tradicionales, como los depósitos a plazo. Si bien no garantiza ganancias constantes, este fondo puede ser una buena opción para quienes están dispuestos a asumir cierto nivel de riesgo en busca de mayores retornos.\n\nEn términos simples, el nivel de riesgo de este fondo se ubica en un punto intermedio en comparación con otras opciones de inversión. A pesar de que puede experimentar fluctuaciones en su valor, especialmente en entornos económicos volátiles, la diversificación de activos ayuda a mitigar parte de este riesgo. Es importante recordar que, en el mundo de las inversiones, el riesgo y la rentabilidad suelen estar relacionados: a mayor riesgo, mayores pueden ser las ganancias pero también las pérdidas potenciales.\n\nEn cuanto al horizonte de inversión recomendado, este tipo de fondo suele ser adecuado para quienes buscan mantener su inversión por un período de al menos 3 a 5 años. Esto se debe a que, al ser un fondo mixto, puede verse afectado por la volatilidad a corto plazo de los mercados financieros, pero tiende a mostrar su verdadero potencial a largo plazo.\n\nUna ventaja de este fondo es su potencial para obtener rendimientos superiores a los de la renta fija tradicional, aunque con un nivel de riesgo moderado. Por otro lado, una posible desventaja podría ser la falta de transparencia en cuanto a la composición exacta de la cartera, lo que dificulta la evaluación detallada de los activos en los que se invierte.\n\nEn resumen, el fondo Progresion Deuda Lp es una opción interesante para inversores con un perfil moderado que buscan un equilibrio entre riesgo y rendimiento. Si estás dispuesto a asumir cierta volatilidad en busca de mayores ganancias a largo plazo, este fondo podría ser adecuado para ti",
  "composicion_portafolio": [],
  "rentabilidad_anual": null,
  "fuente_cmf": true,
  "scraping_success": true,
  "error": null,
  "rut_cmf": null,
  "rut_completo_cmf": null,
  "url_cmf": null,
  "cmf_fund_info": {
    "rut_fondo": "8089-6",
    "rut_admin": "96767630",
    "nombre": "PROGRESION DEUDA LP",
    "full_id": "96767630_8089-6",
    "source": "javascript"
  }
}