{
  "fondo_id": "euroamerica europa",
  "nombre": "Euroamerica Europa",
  "nombre_cmf": "EUROAMERICA EUROPA",
  "tipo_fondo": "Mixto",
  "perfil_riesgo": "Medio",
  "descripcion_amigable": "El fondo Euroamerica Europa es una opción de inversión mixta que combina activos tanto de renta fija como de renta variable en el mercado europeo. Su estrategia de inversión busca lograr un equilibrio entre la estabilidad que ofrecen los bonos y la potencial rentabilidad de las acciones europeas. Este fondo se considera de riesgo medio, lo que significa que puede experimentar fluctuaciones moderadas en su valor, pero también tiene la posibilidad de obtener rendimientos atractivos a mediano plazo.\n\nEste tipo de fondo es adecuado para inversionistas que buscan un equilibrio entre riesgo y potencial de retorno. Si eres un joven inversor chileno con un horizonte de inversión a mediano plazo y estás dispuesto a asumir cierto nivel de riesgo en busca de mayores rendimientos, Euroamerica Europa podría ser una opción a considerar.\n\nEn cuanto a los activos en los que invierte, al ser un fondo mixto, Euroamerica Europa puede tener una variedad de activos en su cartera, que pueden incluir acciones de empresas europeas, bonos corporativos europeos y posiblemente otros instrumentos financieros europeos. Esta diversificación de activos busca reducir el riesgo y maximizar el potencial de retorno a través de la exposición a diferentes sectores y regiones de Europa.\n\nEn términos simples, el nivel de riesgo de este fondo se encuentra en un punto intermedio entre la seguridad de la renta fija y el potencial de crecimiento de la renta variable. Esto significa que si bien existe la posibilidad de obtener ganancias significativas, también se debe estar preparado para enfrentar ciertas fluctuaciones en el valor de la inversión a corto plazo.\n\nEn cuanto al horizonte de inversión recomendado, dado el perfil de riesgo medio del fondo, se sugiere que los inversionistas mantengan una visión a mediano plazo, idealmente de al menos 3 a 5 años. Esto permite que el fondo tenga tiempo suficiente para superar posibles periodos de volatilidad en los mercados y potencialmente lograr rendimientos más sólidos a largo plazo.\n\nVentajas de Euroamerica Europa incluyen la diversificación geográfica que ofrece al invertir en Europa, potencial de crecimiento a través de activos de renta variable y una gestión profesional por parte de la sociedad gestora. Sin embargo, una posible desventaja podría ser la volatilidad inherente a los activos de renta variable, que pueden generar fluctuaciones en el valor de la inversión.\n\nEn resumen, Euroamerica Europa es un fondo mixto de riesgo medio que puede ser adecuado para jóvenes inversion",
  "composicion_portafolio": [],
  "rentabilidad_anual": null,
  "fuente_cmf": true,
  "scraping_success": true,
  "error": null,
  "rut_cmf": null,
  "rut_completo_cmf": null,
  "url_cmf": null,
  "cmf_fund_info": {
    "rut_fondo": "8456-5",
    "rut_admin": "96767630",
    "nombre": "EUROAMERICA EUROPA",
    "full_id": "96767630_8456-5",
    "source": "javascript"
  }
}