{
  "fondo_id": "bonos corporativos",
  "nombre": "Bonos Corporativos",
  "nombre_cmf": "BONOS CORPORATIVOS",
  "tipo_fondo": "Mixto",
  "perfil_riesgo": "Medio",
  "descripcion_amigable": "El fondo de inversión Bonos Corporativos es una excelente opción para aquellos inversores que buscan un equilibrio entre seguridad y rendimiento. Este fondo, de tipo mixto, invierte tanto en bonos emitidos por empresas como en otros instrumentos financieros, buscando obtener ganancias a través de los intereses generados por estos bonos, así como también por la posible apreciación de su valor en el mercado secundario.\n\nEste tipo de fondo es adecuado para inversionistas con un perfil de riesgo medio, es decir, aquellos que están dispuestos a asumir cierto nivel de volatilidad en busca de mayores retornos que los ofrecidos por instrumentos de renta fija tradicionales, como los depósitos a plazo. Aunque el nivel de riesgo no es tan elevado como el de fondos de renta variable, es importante recordar que los bonos corporativos están sujetos a factores como la solvencia de las empresas emisoras y las condiciones del mercado.\n\nEn cuanto a los activos en los que invierte, el fondo Bonos Corporativos se enfoca principalmente en bonos emitidos por empresas chilenas o extranjeras, lo que le otorga una diversificación que puede ayudar a reducir el riesgo asociado a la inversión en un solo emisor. Además, es posible que invierta en otros instrumentos financieros, como bonos soberanos o instrumentos de deuda de corto plazo.\n\nEn términos simples, el nivel de riesgo de este fondo podría compararse con el de caminar por una calle con curvas suaves en lugar de una empinada montaña. Si bien existen riesgos asociados a la solvencia de las empresas emisoras, la diversificación de la cartera y la naturaleza de los bonos corporativos suelen ofrecer una mayor estabilidad en comparación con fondos de renta variable.\n\nPara invertir en el fondo Bonos Corporativos, se recomienda tener un horizonte de inversión a medio o largo plazo, ya que esto permite aprovechar al máximo el potencial de crecimiento de los bonos corporativos y superar posibles fluctuaciones a corto plazo en el mercado.\n\nEn resumen, el fondo Bonos Corporativos es una opción atractiva para inversionistas que buscan un equilibrio entre seguridad y rendimiento, siempre y cuando estén dispuestos a asumir un nivel de riesgo medio. Diversificar la cartera con este tipo de fondo puede ser una estrategia inteligente para aquellos que desean obtener ganancias adicionales a través de los intereses generados por los bonos corporativos. Recuerda siempre consultar con un asesor financiero antes de tomar decisiones de inversión.",
  "composicion_portafolio": [],
  "rentabilidad_anual": null,
  "fuente_cmf": true,
  "scraping_success": true,
  "error": null,
  "rut_cmf": null,
  "rut_completo_cmf": null,
  "url_cmf": null,
  "cmf_fund_info": {
    "rut_fondo": "8953-2",
    "rut_admin": "96767630",
    "nombre": "BONOS CORPORATIVOS",
    "full_id": "96767630_8953-2",
    "source": "javascript"
  }
}