{
  "fondo_id": "fm bch pa usd agresi",
  "nombre": "Fm Bch Pa Usd Agresi",
  "nombre_cmf": "FM BCH PA USD AGRESI",
  "tipo_fondo": "Mixto",
  "perfil_riesgo": "Medio",
  "descripcion_amigable": "Fondo Mutuo Bch Pa Usd Agresi es una alternativa de inversión mixta que combina tanto activos de renta fija como de renta variable. Su objetivo principal es obtener un rendimiento atractivo a largo plazo, asumiendo un nivel de riesgo medio en comparación con otros fondos. Aunque la composición exacta de sus activos principales no está disponible, se puede inferir que busca diversificar su cartera para minimizar riesgos y maximizar ganancias.\n\nEste fondo es adecuado para inversionistas con un perfil moderado, es decir, aquellos que tienen cierta tolerancia al riesgo pero prefieren no asumir niveles extremos de volatilidad en sus inversiones. Si buscas obtener un equilibrio entre la seguridad y el potencial de crecimiento de tu dinero, este fondo podría ser una opción a considerar.\n\nEn cuanto a los activos en los que invierte, el Fm Bch Pa Usd Agresi probablemente destine parte de sus recursos a bonos corporativos de empresas sólidas, así como a acciones de compañías con buen desempeño en el mercado. Esta combinación permite diversificar el riesgo, ya que mientras los bonos ofrecen cierta estabilidad, las acciones pueden potencialmente generar mayores retornos a largo plazo.\n\nEn términos simples, el nivel de riesgo de este fondo se sitúa en un punto intermedio. Aunque no es tan conservador como un fondo de renta fija pura, tampoco es tan agresivo como uno que invierte exclusivamente en acciones de alto riesgo. Es como caminar por un sendero bien marcado en lugar de aventurarse en terreno desconocido: hay riesgos, pero también oportunidades de crecimiento.\n\nPara aquellos jóvenes inversores que buscan hacer crecer su dinero a mediano o largo plazo, el horizonte de inversión recomendado para este fondo sería de al menos 3 a 5 años. Esto permite que la estrategia de inversión se desarrolle y se materialicen los potenciales rendimientos, sin tener que preocuparse por fluctuaciones a corto plazo en los mercados.\n\nEn resumen, el Fm Bch Pa Usd Agresi ofrece una opción equilibrada para inversores que desean diversificar sus inversiones y obtener un rendimiento atractivo sin exponerse a un riesgo extremo. Sin embargo, es importante recordar que todas las inversiones conllevan riesgos, y es fundamental hacer un análisis detallado de tu perfil como inversionista antes de tomar decisiones. ¡Invertir con inteligencia es clave para alcanzar tus metas financieras!",
  "composicion_portafolio": [],
  "rentabilidad_anual": null,
  "fuente_cmf": true,
  "scraping_success": true,
  "error": null,
  "rut_cmf": null,
  "rut_completo_cmf": null,
  "url_cmf": null,
  "cmf_fund_info": {
    "rut_fondo": "10151-6",
    "rut_admin": "96767630",
    "nombre": "FM BCH PA USD AGRESI",
    "full_id": "96767630_10151-6",
    "source": "javascript"
  }
}