{
  "fondo_id": "monetario",
  "nombre": "Monetario",
  "nombre_cmf": "MONETARIO",
  "tipo_fondo": "Mixto",
  "perfil_riesgo": "Medio",
  "descripcion_amigable": "El fondo mutuo Monetario es una opción de inversión mixta que busca generar rendimientos a través de una combinación de activos financieros. Este fondo tiene un perfil de riesgo medio, lo que significa que podría experimentar cierta volatilidad en su valor, pero también ofrece la posibilidad de obtener mayores retornos que un fondo conservador.\n\nEste tipo de fondo suele ser adecuado para inversionistas que buscan un equilibrio entre riesgo y retorno. Por ejemplo, si eres un joven inversionista chileno que está dispuesto a asumir un nivel moderado de riesgo en busca de mayores ganancias, el fondo Monetario podría ser una opción a considerar. Sin embargo, si prefieres una inversión más segura, tal vez deberías explorar fondos de bajo riesgo.\n\nEn cuanto a los activos en los que invierte el fondo Monetario, la composición exacta no está disponible públicamente, pero generalmente suele incluir una combinación de instrumentos financieros como bonos, acciones y efectivo. Esta diversificación puede ayudar a reducir el riesgo asociado con la inversión en un solo tipo de activo.\n\nEn términos simples, el nivel de riesgo de este fondo se sitúa en un punto intermedio, lo que implica que existe la posibilidad de enfrentar fluctuaciones en el valor de la inversión, pero también la oportunidad de obtener rendimientos superiores a los fondos de menor riesgo. Es importante tener en cuenta que el riesgo está presente en toda inversión, por lo que es fundamental analizar tu tolerancia personal al riesgo antes de invertir en este fondo.\n\nEn cuanto al horizonte de inversión recomendado, el fondo Monetario suele ser más adecuado para inversionistas que tienen un horizonte a medio plazo, es decir, que están dispuestos a mantener su inversión durante al menos algunos años. Esto se debe a que el fondo puede experimentar fluctuaciones en el corto plazo, pero tiende a generar mejores resultados a medida que el tiempo avanza.\n\nEn resumen, el fondo Monetario es una alternativa interesante para inversionistas jóvenes en Chile que buscan un equilibrio entre riesgo y retorno. Sin embargo, es importante recordar que toda inversión conlleva cierto nivel de riesgo, por lo que es recomendable consultar con un asesor financiero antes de tomar decisiones de inversión.",
  "composicion_portafolio": [],
  "rentabilidad_anual": null,
  "fuente_cmf": true,
  "scraping_success": true,
  "error": null,
  "rut_cmf": null,
  "rut_completo_cmf": null,
  "url_cmf": null,
  "cmf_fund_info": {
    "rut_fondo": "8059-4",
    "rut_admin": "96767630",
    "nombre": "MONETARIO",
    "full_id": "96767630_8059-4",
    "source": "javascript"
  }
}